CHANGES.rst
CONTRIBUTORS.rst
MANIFEST.in
README.rst
setup.cfg
setup.py
docs/LICENSE.GPL
docs/LICENSE.txt
src/__init__.py
src/netsight/__init__.py
src/netsight.cloudstorage.egg-info/PKG-INFO
src/netsight.cloudstorage.egg-info/SOURCES.txt
src/netsight.cloudstorage.egg-info/dependency_links.txt
src/netsight.cloudstorage.egg-info/entry_points.txt
src/netsight.cloudstorage.egg-info/namespace_packages.txt
src/netsight.cloudstorage.egg-info/not-zip-safe
src/netsight.cloudstorage.egg-info/requires.txt
src/netsight.cloudstorage.egg-info/top_level.txt
src/netsight/cloudstorage/__init__.py
src/netsight/cloudstorage/adapters.py
src/netsight/cloudstorage/configure.zcml
src/netsight/cloudstorage/controlpanel.py
src/netsight/cloudstorage/events.py
src/netsight/cloudstorage/exceptions.py
src/netsight/cloudstorage/interfaces.py
src/netsight/cloudstorage/monkeypatches.py
src/netsight/cloudstorage/subscribers.py
src/netsight/cloudstorage/tasks.py
src/netsight/cloudstorage/testing.py
src/netsight/cloudstorage/upgrade.py
src/netsight/cloudstorage/utils.py
src/netsight/cloudstorage/Extensions/install.py
src/netsight/cloudstorage/browser/__init__.py
src/netsight/cloudstorage/browser/configure.zcml
src/netsight/cloudstorage/browser/download.py
src/netsight/cloudstorage/browser/status_viewlet.pt
src/netsight/cloudstorage/browser/viewlets.py
src/netsight/cloudstorage/browser/views.py
src/netsight/cloudstorage/profiles/default/browserlayer.xml
src/netsight/cloudstorage/profiles/default/controlpanel.xml
src/netsight/cloudstorage/profiles/default/metadata.xml
src/netsight/cloudstorage/profiles/default/registry.xml
src/netsight/cloudstorage/profiles/uninstall/browserlayer.xml
src/netsight/cloudstorage/tests/__init__.py
src/netsight/cloudstorage/tests/base.py
src/netsight/cloudstorage/tests/test_adapter.py