Metadata-Version: 1.1
Name: netsight.cloudstorage
Version: 1.8.1
Summary: Allows you to store large files in the cloud
Home-page: https://github.com/netsight/netsight.cloudstorage
Author: Ben Cole
Author-email: benc@netsight.co.uk
License: gpl
Platform: UNKNOWN
Classifier: Environment :: Web Environment
Classifier: Framework :: Plone
Classifier: Operating System :: OS Independent
Classifier: Programming Language :: Python
Classifier: Programming Language :: Python :: 2.7
Classifier: Topic :: Software Development :: Libraries :: Python Modules
